default.mp3
pytest_tick.py
pytest_tick-0.1.0.dist-info/entry_points.txt
pytest_tick-0.1.0.dist-info/WHEEL
pytest_tick-0.1.0.dist-info/METADATA
pytest_tick-0.1.0.dist-info/RECORD
