Metadata-Version: 2.1
Name: pytest-tick
Version: 0.1.0
Summary: Ticking on tests
Home-page: https://github.com/platonoff-dev/pytest-tick
Author: Platonov Anatoliy
Author-email: p4m.dev@gmail.com
Requires-Python: >=3.6,<4.0
Classifier: Development Status :: 5 - Production/Stable
Classifier: Framework :: Pytest
Classifier: Intended Audience :: Developers
Classifier: Intended Audience :: Information Technology
Classifier: License :: OSI Approved :: Apache Software License
Classifier: Programming Language :: Python :: 3
Classifier: Programming Language :: Python :: 3.6
Classifier: Programming Language :: Python :: 3.7
Classifier: Programming Language :: Python :: 3.8
Classifier: Programming Language :: Python :: 3.9
Classifier: Topic :: Internet
Classifier: Topic :: Software Development
Classifier: Topic :: Software Development :: Libraries
Classifier: Topic :: Software Development :: Libraries :: Python Modules
Requires-Dist: playsound (>=1.3.0,<2.0.0)
Requires-Dist: pytest (>=6.2.5,<7.0.0)
Project-URL: Repository, https://github.com/platonoff-dev/pytest-tick
